[
  {
    "id": "history2_ch1_Q1",
    "chapter": "中国近现代史",
    "type": "single",
    "stem": "history 示例题 1：关于中国近现代史的基础练习。",
    "options": [
      "A",
      "B",
      "C",
      "D"
    ],
    "answer": 0,
    "solution": "中国近现代史 相关练习答案示例：A。",
    "tags": [
      "history",
      "必修2",
      "中国近现代史"
    ]
  },
  {
    "id": "history2_ch1_Q2",
    "chapter": "中国近现代史",
    "type": "single",
    "stem": "history 示例题 2：关于中国近现代史的基础练习。",
    "options": [
      "A",
      "B",
      "C",
      "D"
    ],
    "answer": 0,
    "solution": "中国近现代史 相关练习答案示例：A。",
    "tags": [
      "history",
      "必修2",
      "中国近现代史"
    ]
  },
  {
    "id": "history2_ch1_Q3",
    "chapter": "中国近现代史",
    "type": "single",
    "stem": "history 示例题 3：关于中国近现代史的基础练习。",
    "options": [
      "A",
      "B",
      "C",
      "D"
    ],
    "answer": 0,
    "solution": "中国近现代史 相关练习答案示例：A。",
    "tags": [
      "history",
      "必修2",
      "中国近现代史"
    ]
  },
  {
    "id": "history2_ch1_Q4",
    "chapter": "中国近现代史",
    "type": "single",
    "stem": "history 示例题 4：关于中国近现代史的基础练习。",
    "options": [
      "A",
      "B",
      "C",
      "D"
    ],
    "answer": 0,
    "solution": "中国近现代史 相关练习答案示例：A。",
    "tags": [
      "history",
      "必修2",
      "中国近现代史"
    ]
  },
  {
    "id": "history2_ch1_Q5",
    "chapter": "中国近现代史",
    "type": "single",
    "stem": "history 示例题 5：关于中国近现代史的基础练习。",
    "options": [
      "A",
      "B",
      "C",
      "D"
    ],
    "answer": 0,
    "solution": "中国近现代史 相关练习答案示例：A。",
    "tags": [
      "history",
      "必修2",
      "中国近现代史"
    ]
  },
  {
    "id": "history2_ch1_Q6",
    "chapter": "中国近现代史",
    "type": "single",
    "stem": "history 示例题 6：关于中国近现代史的基础练习。",
    "options": [
      "A",
      "B",
      "C",
      "D"
    ],
    "answer": 0,
    "solution": "中国近现代史 相关练习答案示例：A。",
    "tags": [
      "history",
      "必修2",
      "中国近现代史"
    ]
  },
  {
    "id": "history2_ch1_Q7",
    "chapter": "中国近现代史",
    "type": "single",
    "stem": "history 示例题 7：关于中国近现代史的基础练习。",
    "options": [
      "A",
      "B",
      "C",
      "D"
    ],
    "answer": 0,
    "solution": "中国近现代史 相关练习答案示例：A。",
    "tags": [
      "history",
      "必修2",
      "中国近现代史"
    ]
  },
  {
    "id": "history2_ch1_Q8",
    "chapter": "中国近现代史",
    "type": "single",
    "stem": "history 示例题 8：关于中国近现代史的基础练习。",
    "options": [
      "A",
      "B",
      "C",
      "D"
    ],
    "answer": 0,
    "solution": "中国近现代史 相关练习答案示例：A。",
    "tags": [
      "history",
      "必修2",
      "中国近现代史"
    ]
  },
  {
    "id": "history2_ch1_Q9",
    "chapter": "中国近现代史",
    "type": "single",
    "stem": "history 示例题 9：关于中国近现代史的基础练习。",
    "options": [
      "A",
      "B",
      "C",
      "D"
    ],
    "answer": 0,
    "solution": "中国近现代史 相关练习答案示例：A。",
    "tags": [
      "history",
      "必修2",
      "中国近现代史"
    ]
  },
  {
    "id": "history2_ch1_Q10",
    "chapter": "中国近现代史",
    "type": "single",
    "stem": "history 示例题 10：关于中国近现代史的基础练习。",
    "options": [
      "A",
      "B",
      "C",
      "D"
    ],
    "answer": 0,
    "solution": "中国近现代史 相关练习答案示例：A。",
    "tags": [
      "history",
      "必修2",
      "中国近现代史"
    ]
  }
]